_hide_from_traceback.cpython-311-i386-linux-gnu.so
hide_from_traceback-1.0.1.dist-info/top_level.txt
hide_from_traceback-1.0.1.dist-info/METADATA
hide_from_traceback-1.0.1.dist-info/RECORD
hide_from_traceback-1.0.1.dist-info/WHEEL
hide_from_traceback-1.0.1.dist-info/licenses/LICENSE
hide_from_traceback/py.typed
hide_from_traceback/__init__.py
_hide_from_traceback/__init__.pyi
_hide_from_traceback/py.typed
