Metadata-Version: 2.4
Name: hide_from_traceback
Version: 1.0.1
Summary: Omit utility functions from tracebacks.
Project-URL: Repository, https://github.com/emosenkis/hide_from_traceback
Requires-Python: >=3.9
License-File: LICENSE
Requires-Dist: typing-extensions>=4.4.0; python_version < "3.10"
Dynamic: license-file
